searchfilms/__init__.py
searchfilms-0.0.2.dist-info/LICENSE
searchfilms-0.0.2.dist-info/METADATA
searchfilms-0.0.2.dist-info/WHEEL
searchfilms-0.0.2.dist-info/top_level.txt
searchfilms-0.0.2.dist-info/RECORD
